mcp_ical/__init__.py
mcp_ical/ical.py
mcp_ical/models.py
mcp_ical/server.py
mseep_mcp_ical-0.1.6.dist-info/licenses/LICENSE
mseep_mcp_ical-0.1.6.dist-info/METADATA
mseep_mcp_ical-0.1.6.dist-info/WHEEL
mseep_mcp_ical-0.1.6.dist-info/entry_points.txt
mseep_mcp_ical-0.1.6.dist-info/top_level.txt
mseep_mcp_ical-0.1.6.dist-info/RECORD
