Metadata-Version: 2.4
Name: mseep-mcp-ical
Version: 0.1.6
Summary: A Model Context Protocol server providing tools for CRUD operations for the mac-os calendar
Author-email: mseep <support@skydeck.ai>
Requires-Python: >=3.12
License-File: LICENSE
Requires-Dist: loguru>=0.7.3
Requires-Dist: mcp[cli]>=1.2.1
Requires-Dist: pyobjc>=11.0
Dynamic: license-file
